{
  "$schema": "https://json.schemastore.org/tsconfig",
  "compilerOptions": {
    "esModuleInterop": true,
    "moduleResolution": "Node",

    "downlevelIteration": true,
    "skipLibCheck": true,
    "forceConsistentCasingInFileNames": true,
    "removeComments": true,
    "allowUnreachableCode": false,
    "allowUnusedLabels": false,
    "strict": true,
    "strictFunctionTypes": true,
    "strictNullChecks": true,
    "strictBindCallApply": true,
    "strictPropertyInitialization": true,
    "noUnusedLocals": true,
    "noImplicitAny": true,
    "noImplicitOverride": true,
    "noImplicitReturns": false,
    "noImplicitThis": true,
    "noPropertyAccessFromIndexSignature": false,
    "noFallthroughCasesInSwitch": true,
    "resolveJsonModule": true,
    "noUncheckedIndexedAccess": true,
    "useUnknownInCatchVariables": false
  },
  "exclude": ["node_modules", "dist", ".next"]
}
